game2048/__init__.py
game2048/cli.py
game2048/game.py
game2048/tui.py
tui_2048-1.0.0.dist-info/licenses/LICENSE
tui_2048-1.0.0.dist-info/METADATA
tui_2048-1.0.0.dist-info/WHEEL
tui_2048-1.0.0.dist-info/entry_points.txt
tui_2048-1.0.0.dist-info/top_level.txt
tui_2048-1.0.0.dist-info/RECORD
