Metadata-Version: 2.4
Name: tui-2048
Version: 1.0.0
Summary: A terminal-based 2048 game with colorful TUI
Author-email: Pratik Singhal <ps06756@gmail.com>
License: MIT
Project-URL: Homepage, https://github.com/yourusername/tui-2048
Project-URL: Repository, https://github.com/yourusername/tui-2048
Project-URL: Issues, https://github.com/yourusername/tui-2048/issues
Keywords: 2048,game,terminal,tui,curses,cli
Classifier: Development Status :: 4 - Beta
Classifier: Environment :: Console
Classifier: Environment :: Console :: Curses
Classifier: Intended Audience :: End Users/Desktop
Classifier: License :: OSI Approved :: MIT License
Classifier: Operating System :: OS Independent
Classifier: Programming Language :: Python :: 3
Classifier: Programming Language :: Python :: 3.7
Classifier: Programming Language :: Python :: 3.8
Classifier: Programming Language :: Python :: 3.9
Classifier: Programming Language :: Python :: 3.10
Classifier: Programming Language :: Python :: 3.11
Classifier: Programming Language :: Python :: 3.12
Classifier: Topic :: Games/Entertainment :: Puzzle Games
Requires-Python: >=3.7
License-File: LICENSE
Dynamic: license-file
